raid/__init__.py
raid/ast_token_activator.py
raid/extract_patterns.py
raid/generate_files.py
raid/label_dictionary.py
raid/raid_pipeline.py
raid_tool-5.1.0.dist-info/METADATA
raid_tool-5.1.0.dist-info/WHEEL
raid_tool-5.1.0.dist-info/dependency_links.txt
raid_tool-5.1.0.dist-info/entry_points.txt
raid_tool-5.1.0.dist-info/top_level.txt
raid_tool-5.1.0.dist-info/RECORD
