Metadata-Version: 2.1
Name: raid-tool
Version: 5.1.0
Summary: RAID: Rapid Automated Interpretability Datasets tool
Home-page: https://github.com/arushisharma17/RAID
Author: Hrishikesha Kyathsandra, Zeynep Oghan, Arushi Sharma
Author-email: hk.hrishi30@gmail.com
Classifier: Programming Language :: Python :: 3
Classifier: License :: OSI Approved :: MIT License
Classifier: Operating System :: OS Independent
Requires-Python: >=3.6
Requires-Dist: asttokens==2.4.1
Requires-Dist: attrs==24.2.0
Requires-Dist: backcall==0.2.0
Requires-Dist: beautifulsoup4==4.12.3
Requires-Dist: bleach==6.1.0
Requires-Dist: blinker==1.8.2
Requires-Dist: certifi==2024.8.30
Requires-Dist: charset-normalizer==3.4.0
Requires-Dist: click==8.1.7
Requires-Dist: colorama==0.4.6
Requires-Dist: decorator==5.1.1
Requires-Dist: defusedxml==0.7.1
Requires-Dist: docopt==0.6.2
Requires-Dist: executing==2.1.0
Requires-Dist: fastjsonschema==2.20.0
Requires-Dist: Flask==3.0.3
Requires-Dist: idna==3.10
Requires-Dist: ipython==8.12.3
Requires-Dist: itsdangerous==2.2.0
Requires-Dist: jedi==0.19.1
Requires-Dist: Jinja2==3.1.4
Requires-Dist: jsonschema==4.23.0
Requires-Dist: jsonschema-specifications==2024.10.1
Requires-Dist: jupyter_client==8.6.3
Requires-Dist: jupyter_core==5.7.2
Requires-Dist: jupyterlab_pygments==0.3.0
Requires-Dist: MarkupSafe==2.1.5
Requires-Dist: matplotlib-inline==0.1.7
Requires-Dist: mistune==3.0.2
Requires-Dist: nbclient==0.10.0
Requires-Dist: nbconvert==7.16.4
Requires-Dist: nbformat==5.10.4
Requires-Dist: packaging==24.1
Requires-Dist: pandocfilters==1.5.1
Requires-Dist: parso==0.8.4
Requires-Dist: pickleshare==0.7.5
Requires-Dist: pipreqs==0.5.0
Requires-Dist: platformdirs==4.3.6
Requires-Dist: prompt_toolkit==3.0.48
Requires-Dist: pure_eval==0.2.3
Requires-Dist: Pygments==2.18.0
Requires-Dist: python-dateutil==2.9.0.post0
Requires-Dist: pywin32==308; platform_system == "Windows"
Requires-Dist: pyzmq==26.2.0
Requires-Dist: referencing==0.35.1
Requires-Dist: requests==2.32.3
Requires-Dist: rpds-py==0.20.0
Requires-Dist: six==1.16.0
Requires-Dist: soupsieve==2.6
Requires-Dist: stack-data==0.6.3
Requires-Dist: tinycss2==1.3.0
Requires-Dist: tornado==6.4.1
Requires-Dist: traitlets==5.14.3
Requires-Dist: urllib3==2.2.3
Requires-Dist: wcwidth==0.2.13
Requires-Dist: webencodings==0.5.1
Requires-Dist: Werkzeug==3.0.4
Requires-Dist: yarg==0.1.9
Requires-Dist: contourpy==1.3.0
Requires-Dist: cycler==0.12.1
Requires-Dist: dill==0.3.4
Requires-Dist: filelock==3.16.1
Requires-Dist: fonttools==4.54.1
Requires-Dist: fsspec==2024.9.0
Requires-Dist: graphviz==0.20.3
Requires-Dist: h5py==3.12.1
Requires-Dist: huggingface-hub==0.25.1
Requires-Dist: imbalanced-learn==0.12.4
Requires-Dist: joblib==1.4.2
Requires-Dist: kiwisolver==1.4.7
Requires-Dist: matplotlib==3.9.2
Requires-Dist: memory-profiler==0.61.0
Requires-Dist: mpmath==1.3.0
Requires-Dist: networkx==3.3
Requires-Dist: numpy==1.26.4
Requires-Dist: pandas==2.2.3
Requires-Dist: pillow==10.4.0
Requires-Dist: psutil==6.0.0
Requires-Dist: pyparsing==3.1.4
Requires-Dist: pytz==2024.2
Requires-Dist: PyYAML==6.0.2
Requires-Dist: regex==2024.9.11
Requires-Dist: safetensors==0.4.5
Requires-Dist: scikit-learn==1.5.2
Requires-Dist: scipy==1.14.1
Requires-Dist: seaborn==0.11.1
Requires-Dist: svgwrite==1.4.1
Requires-Dist: sympy==1.13.3
Requires-Dist: threadpoolctl==3.5.0
Requires-Dist: tokenizers==0.20.0
Requires-Dist: torch==2.4.1
Requires-Dist: tqdm==4.66.5
Requires-Dist: transformers==4.45.1
Requires-Dist: tree-sitter==0.23.0
Requires-Dist: tree-sitter-java==0.23.2
Requires-Dist: tree-sitter-python==0.23.2
Requires-Dist: typing_extensions==4.12.2
Requires-Dist: tzdata==2024.2
